{
  "year": 2001,
  "bill": "D.R 7/2001 - Entertainments Duty (Amendment) Bill 2001 (Passed)",
  "id": "0_2001_48",
  "children": [
    {
      "text": "D.R 7/2001",
      "id": "0_2001_48_1"
    },
    {
      "text": "First reading:",
      "id": "0_2001_48_2"
    },
    {
      "text": "The second reading:",
      "id": "0_2001_48_2"
    },
    {
      "text": "Presented by:",
      "id": "0_2001_48_3"
    },
    {
      "text": "Passed At:",
      "id": "0_2001_48_2"
    },
    {
      "text": "Presented by:",
      "id": "0_2001_48_3"
    }
  ],
  "document": "/files/billindex/pdf/2001/Bill DR 7.pdf"
}