{
  "year": 2022,
  "bill": "D.R.26/2022 - RUU Cukai Pelancongan (Pindaan) 2022 (Lulus)",
  "id": "0_2022_21",
  "children": [
    {
      "text": "D.R.26/2022",
      "id": "0_2022_21_1"
    },
    {
      "text": "Bacaan Pertama Pada:20/07/2022",
      "id": "0_2022_21_2"
    },
    {
      "text": "Bacaan Kedua Pada:03/08/2022",
      "id": "0_2022_21_2"
    },
    {
      "text": "Dibentang Oleh:YB Tuan Haji Yamani Hafez bin Musa \u2013 Timbalan Menteri Kewangan II",
      "id": "0_2022_21_3"
    },
    {
      "text": "Diluluskan Pada:03/08/2022",
      "id": "0_2022_21_2"
    },
    {
      "text": "Dibentang Oleh:YB Tuan Haji Yamani Hafez bin Musa \u2013 Timbalan Menteri Kewangan II",
      "id": "0_2022_21_3"
    }
  ],
  "document": "/files/billindex/pdf/2022/DR 26 - bm.pdf"
}