{
  "year": 1991,
  "bill": "D.R.39/1991 - Legal Profession (Amendment) Bill 1991 (Passed)",
  "id": "0_1991_32",
  "children": [
    {
      "text": "D.R.39/1991",
      "id": "0_1991_32_1"
    },
    {
      "text": "First reading:",
      "id": "0_1991_32_2"
    },
    {
      "text": "The second reading:",
      "id": "0_1991_32_2"
    },
    {
      "text": "Presented by:",
      "id": "0_1991_32_3"
    },
    {
      "text": "Passed At:",
      "id": "0_1991_32_2"
    },
    {
      "text": "Presented by:",
      "id": "0_1991_32_3"
    }
  ],
  "document": "/files/billindex/pdf/1991/DR391991E.pdf"
}