{
  "year": 2016,
  "bill": "D.R. 19/2016 - Emblems and Names (Prevention of Improper Use) (Amendment) Bill 2016 (Passed)",
  "id": "0_2016_11",
  "children": [
    {
      "text": "D.R. 19/2016",
      "id": "0_2016_11_1"
    },
    {
      "text": "First reading:21/11/2016",
      "id": "0_2016_11_2"
    },
    {
      "text": "The second reading:23/11/2016",
      "id": "0_2016_11_2"
    },
    {
      "text": "Presented by:YB Dato' Sri Azalina binti Dato' Othman Said -  Menteri Di Jabatan Perdana Menteri",
      "id": "0_2016_11_3"
    },
    {
      "text": "Passed At:23/11/2016",
      "id": "0_2016_11_2"
    },
    {
      "text": "Presented by:YB Dato' Sri Azalina binti Dato' Othman Said -  Menteri Di Jabatan Perdana Menteri",
      "id": "0_2016_11_3"
    }
  ],
  "document": "/files/billindex/pdf/2016/D.R. 19_2016_eng.pdf"
}