{
  "year": 2011,
  "bill": "D.R.02/2011 - Promotion of Investments (Amendment) Bill 2011 (Passed)",
  "id": "0_2011_1",
  "children": [
    {
      "text": "D.R.02/2011",
      "id": "0_2011_1_1"
    },
    {
      "text": "First reading:",
      "id": "0_2011_1_2"
    },
    {
      "text": "The second reading:",
      "id": "0_2011_1_2"
    },
    {
      "text": "Presented by:",
      "id": "0_2011_1_3"
    },
    {
      "text": "Passed At:15/06/2011",
      "id": "0_2011_1_2"
    },
    {
      "text": "Presented by:Y.B. Dato Mukhriz Tun Dr. Mahathir, Timbalan Menteri Perdagangan Antarabangsa dan Industri",
      "id": "0_2011_1_3"
    }
  ],
  "document": "/files/billindex/pdf/2011/DR022011E.pdf"
}