{
  "year": 2021,
  "bill": "D.R 6/2021 - Small Estates (Distribution) (Amendment) Bill 2021 (Passed)",
  "id": "0_2021_5",
  "children": [
    {
      "text": "D.R 6/2021",
      "id": "0_2021_5_1"
    },
    {
      "text": "First reading:11/10/2021",
      "id": "0_2021_5_2"
    },
    {
      "text": "The second reading:26/10/2021",
      "id": "0_2021_5_2"
    },
    {
      "text": "Presented by:YB Datuk Seri Takiyuddin bin Hassan - Menteri Tenaga dan Sumber Asli",
      "id": "0_2021_5_3"
    },
    {
      "text": "Passed At:26/10/2021",
      "id": "0_2021_5_2"
    },
    {
      "text": "Presented by:YB Datuk Seri Takiyuddin bin Hassan - Menteri Tenaga dan Sumber Asli",
      "id": "0_2021_5_3"
    }
  ],
  "document": "/files/billindex/pdf/2021/DR 6 (BI) Teks.pdf"
}