{
  "year": 2017,
  "bill": "D.R.23/2017 - Lembaga Kemajuan Johor Tenggara (Amendment) Bill 2017 (Passed)",
  "id": "0_2017_22",
  "children": [
    {
      "text": "D.R.23/2017",
      "id": "0_2017_22_1"
    },
    {
      "text": "First reading:25/07/2017",
      "id": "0_2017_22_2"
    },
    {
      "text": "The second reading:08/08/2017",
      "id": "0_2017_22_2"
    },
    {
      "text": "Presented by:YB Datuk Alexander Nanta Linggi - Tim. Men. KKLW",
      "id": "0_2017_22_3"
    },
    {
      "text": "Passed At:08/08/2017",
      "id": "0_2017_22_2"
    },
    {
      "text": "Presented by:YB Dato' Sri Ismail Sabri Bin Yaakob - Menteri KKLW",
      "id": "0_2017_22_3"
    }
  ],
  "document": "/files/billindex/pdf/2017/D.R. 23_2017 (eng).pdf"
}