{
  "year": 2019,
  "bill": "D.R 3/2019 - RUU Eksais (Pindaan) 2019 (Lulus)",
  "id": "0_2019_2",
  "children": [
    {
      "text": "D.R 3/2019",
      "id": "0_2019_2_1"
    },
    {
      "text": "Bacaan Pertama Pada:03/04/2019",
      "id": "0_2019_2_2"
    },
    {
      "text": "Bacaan Kedua Pada:08/04/2019",
      "id": "0_2019_2_2"
    },
    {
      "text": "Dibentang Oleh:YB Dato' Haji Amiruddin Bin Haji Hamzah \u2013 Tim. Menteri Kewangan",
      "id": "0_2019_2_3"
    },
    {
      "text": "Diluluskan Pada:08/04/2019",
      "id": "0_2019_2_2"
    },
    {
      "text": "Dibentang Oleh:YB Dato' Haji Amiruddin Bin Haji Hamzah \u2013 Tim. Menteri Kewangan",
      "id": "0_2019_2_3"
    }
  ],
  "document": "/files/billindex/pdf/2019/DR 3 BM.pdf"
}