{
  "year": 1992,
  "bill": "D.R.38/1992 - Land Acquisition (Amendment) Bill 1992 (Passed)",
  "id": "0_1992_17",
  "children": [
    {
      "text": "D.R.38/1992",
      "id": "0_1992_17_1"
    },
    {
      "text": "First reading:",
      "id": "0_1992_17_2"
    },
    {
      "text": "The second reading:",
      "id": "0_1992_17_2"
    },
    {
      "text": "Presented by:",
      "id": "0_1992_17_3"
    },
    {
      "text": "Passed At:",
      "id": "0_1992_17_2"
    },
    {
      "text": "Presented by:",
      "id": "0_1992_17_3"
    }
  ],
  "document": "/files/billindex/pdf/1992/DR381992E.pdf"
}