{
  "year": 2016,
  "bill": "D.R. 23/2016 - Civil Aviation (Amendment) Bill 2016 (Passed)",
  "id": "0_2016_16",
  "children": [
    {
      "text": "D.R. 23/2016",
      "id": "0_2016_16_1"
    },
    {
      "text": "First reading:22/11/2016",
      "id": "0_2016_16_2"
    },
    {
      "text": "The second reading:23/11/2016",
      "id": "0_2016_16_2"
    },
    {
      "text": "Presented by:YB Dato' Sri Liow Tiong Lai - Menteri Pengangkutan",
      "id": "0_2016_16_3"
    },
    {
      "text": "Passed At:23/11/2016",
      "id": "0_2016_16_2"
    },
    {
      "text": "Presented by:YB Dato' Sri Liow Tiong Lai - Menteri Pengangkutan",
      "id": "0_2016_16_3"
    }
  ],
  "document": "/files/billindex/pdf/2016/D.R. 23_2016_eng.pdf"
}