{
  "year": 2001,
  "bill": "D.R 45/2001 - Malaysian Examinations Council (Amendment) Bill 2001 (Passed)",
  "id": "0_2001_39",
  "children": [
    {
      "text": "D.R 45/2001",
      "id": "0_2001_39_1"
    },
    {
      "text": "First reading:",
      "id": "0_2001_39_2"
    },
    {
      "text": "The second reading:",
      "id": "0_2001_39_2"
    },
    {
      "text": "Presented by:",
      "id": "0_2001_39_3"
    },
    {
      "text": "Passed At:",
      "id": "0_2001_39_2"
    },
    {
      "text": "Presented by:",
      "id": "0_2001_39_3"
    }
  ],
  "document": "/files/billindex/pdf/2001/Bill DR 45.pdf"
}